asgi_ipc/__init__.py
asgi_ipc/core.py
asgi_ipc/store.py
asgi_ipc-1.4.2.dist-info/DESCRIPTION.rst
asgi_ipc-1.4.2.dist-info/METADATA
asgi_ipc-1.4.2.dist-info/RECORD
asgi_ipc-1.4.2.dist-info/WHEEL
asgi_ipc-1.4.2.dist-info/metadata.json
asgi_ipc-1.4.2.dist-info/top_level.txt
