Metadata-Version: 2.0
Name: asgi-ipc
Version: 1.4.2
Summary: Posix IPC-backed ASGI channel layer implementation
Home-page: http://github.com/django/asgi_ipc/
Author: Django Software Foundation
Author-email: foundation@djangoproject.com
License: BSD
Platform: UNKNOWN
Requires-Dist: asgiref (~=1.1.2)
Requires-Dist: msgpack-python
Requires-Dist: posix-ipc (>=1.0.0)
Requires-Dist: six
